<Ui xmlns="http://www.blizzard.com/wow/ui/" xmlns:xsi="http://www.w3.org/2001/XMLSchema-instance" xsi:schemaLocation="http://www.blizzard.com/wow/ui/
..\Blizzard_SharedXML\UI.xsd">
	<Button name="HousingInspectModeManagerFrame" mixin="HousingInspectModeManagerMixin" parent="UIParent" propagateKeyboardInput="true" propagateMouseInput="Both" frameStrata="LOW" frameLevel="1">
		<Scripts>
			<OnLoad method="OnLoad"/>
			<OnShow method="OnShow"/>
			<OnHide method="OnHide"/>
			<OnClick method="OnClick"/>
			<OnEnter method="OnEnter"/>
			<OnLeave method="OnLeave"/>
			<OnEvent method="OnEvent"/>
		</Scripts>
	</Button>
</Ui>
